pandoramoon/__init__.py
pandoramoon/eclipse.py
pandoramoon/ellipse.py
pandoramoon/grids.py
pandoramoon/helpers.py
pandoramoon/occult.py
pandoramoon/pandora.py
pandoramoon/star_colors.csv
pandoramoon/version.py
pandoramoon-1.2.dist-info/LICENSE
pandoramoon-1.2.dist-info/METADATA
pandoramoon-1.2.dist-info/WHEEL
pandoramoon-1.2.dist-info/top_level.txt
pandoramoon-1.2.dist-info/RECORD
