Metadata-Version: 2.1
Name: pandoramoon
Version: 1.2
Summary: Exomoon transit detection algorithm
Home-page: https://github.com/hippke/pandora
Author: Michael Hippke
Author-email: michael@hippke.org
License: GPL3
Platform: UNKNOWN
License-File: LICENSE
Requires-Dist: numpy (>=1.21)
Requires-Dist: numba (>=0.54)
Requires-Dist: tqdm
Requires-Dist: matplotlib
